{
  "db_name": "PostgreSQL",
  "query": "\n                    UPDATE webhook.subscription\n                    SET is_enabled = $1, description = $2, metadata = $3, labels = $4, retry_config = $5\n                    WHERE subscription__id = $6 AND application__id = $7 AND deleted_at IS NULL\n                    RETURNING subscription__id, is_enabled, description, secret, metadata, labels, target__id, created_at, retry_config\n                ",
  "describe": {
    "columns": [
      {
        "ordinal": 0,
        "name": "subscription__id",
        "type_info": "Uuid"
      },
      {
        "ordinal": 1,
        "name": "is_enabled",
        "type_info": "Bool"
      },
      {
        "ordinal": 2,
        "name": "description",
        "type_info": "Text"
      },
      {
        "ordinal": 3,
        "name": "secret",
        "type_info": "Uuid"
      },
      {
        "ordinal": 4,
        "name": "metadata",
        "type_info": "Jsonb"
      },
      {
        "ordinal": 5,
        "name": "labels",
        "type_info": "Jsonb"
      },
      {
        "ordinal": 6,
        "name": "target__id",
        "type_info": "Uuid"
      },
      {
        "ordinal": 7,
        "name": "created_at",
        "type_info": "Timestamptz"
      },
      {
        "ordinal": 8,
        "name": "retry_config",
        "type_info": "Jsonb"
      }
    ],
    "parameters": {
      "Left": [
        "Bool",
        "Text",
        "Jsonb",
        "Jsonb",
        "Jsonb",
        "Uuid",
        "Uuid"
      ]
    },
    "nullable": [
      false,
      false,
      true,
      false,
      false,
      false,
      false,
      false,
      false
    ]
  },
  "hash": "54d72fc25db344ac17aa4c13c916dd4b32d9cd2b63ac75e6e94266496b477be6"
}
